napari_cookiecut/__init__.py
napari_cookiecut/_reader.py
napari_cookiecut/_sample_data.py
napari_cookiecut/_version.py
napari_cookiecut/_widget.py
napari_cookiecut/_writer.py
napari_cookiecut/napari.yaml
napari_cookiecut/_tests/__init__.py
napari_cookiecut/_tests/test_reader.py
napari_cookiecut/_tests/test_sample_data.py
napari_cookiecut/_tests/test_widget.py
napari_cookiecut/_tests/test_writer.py
napari_cookiecut-0.1.1.dist-info/LICENSE
napari_cookiecut-0.1.1.dist-info/METADATA
napari_cookiecut-0.1.1.dist-info/WHEEL
napari_cookiecut-0.1.1.dist-info/entry_points.txt
napari_cookiecut-0.1.1.dist-info/top_level.txt
napari_cookiecut-0.1.1.dist-info/RECORD
