Metadata-Version: 2.1
Name: napari-cookiecut
Version: 0.1.1
Summary: Fixed cut
Home-page: https://github.com/seankmartin/napari-cookiecut
Author: Sean Martin
Author-email: martins7@tcd.ie
License: BSD-3-Clause
Project-URL: Bug Tracker, https://github.com/seankmartin/napari-cookiecut/issues
Project-URL: Documentation, https://github.com/seankmartin/napari-cookiecut#README.md
Project-URL: Source Code, https://github.com/seankmartin/napari-cookiecut
Project-URL: User Support, https://github.com/seankmartin/napari-cookiecut/issues
Classifier: Development Status :: 2 - Pre-Alpha
Classifier: Framework :: napari
Classifier: Intended Audience :: Developers
Classifier: License :: OSI Approved :: BSD License
Classifier: Operating System :: OS Independent
Classifier: Programming Language :: Python
Classifier: Programming Language :: Python :: 3
Classifier: Programming Language :: Python :: 3 :: Only
Classifier: Programming Language :: Python :: 3.8
Classifier: Programming Language :: Python :: 3.9
Classifier: Programming Language :: Python :: 3.10
Classifier: Topic :: Scientific/Engineering :: Image Processing
Requires-Python: >=3.8
License-File: LICENSE
Requires-Dist: numpy
Requires-Dist: magicgui
Requires-Dist: qtpy
Provides-Extra: testing
Requires-Dist: tox ; extra == 'testing'
Requires-Dist: pytest ; extra == 'testing'
Requires-Dist: pytest-cov ; extra == 'testing'
Requires-Dist: pytest-qt ; extra == 'testing'
Requires-Dist: napari ; extra == 'testing'
Requires-Dist: pyqt5 ; extra == 'testing'
